LICENSE
README.md
pyproject.toml
setup.cfg
setup.py
nats/__init__.py
nats/errors.py
nats/nuid.py
nats/py.typed
nats/aio/__init__.py
nats/aio/client.py
nats/aio/errors.py
nats/aio/msg.py
nats/aio/subscription.py
nats/aio/transport.py
nats/js/__init__.py
nats/js/api.py
nats/js/client.py
nats/js/errors.py
nats/js/kv.py
nats/js/manager.py
nats/js/object_store.py
nats/protocol/__init__.py
nats/protocol/command.py
nats/protocol/parser.py
nats_py.egg-info/PKG-INFO
nats_py.egg-info/SOURCES.txt
nats_py.egg-info/dependency_links.txt
nats_py.egg-info/requires.txt
nats_py.egg-info/top_level.txt
nats_py.egg-info/zip-safe
tests/test_client.py
tests/test_client_async_await.py
tests/test_client_nkeys.py
tests/test_client_v2.py
tests/test_client_websocket.py
tests/test_js.py
tests/test_nuid.py
tests/test_parser.py