Metadata-Version: 2.1
Name: nats-py
Version: 2.4.0
Summary: NATS client for Python
Author-email: Waldemar Quevedo <wally@synadia.com>
License: Apache 2 License
Project-URL: Homepage, https://github.com/nats-io/nats.py
Project-URL: Bug Tracker, https://github.com/nats-io/nats.py/issues
Classifier: License :: OSI Approved :: Apache Software License
Classifier: Intended Audience :: Developers
Classifier: Programming Language :: Python
Classifier: Programming Language :: Python :: 3
Classifier: Programming Language :: Python :: 3.7
Classifier: Programming Language :: Python :: 3.8
Classifier: Programming Language :: Python :: 3.9
Classifier: Programming Language :: Python :: 3.10
Classifier: Programming Language :: Python :: 3.11
Requires-Python: >=3.7
License-File: LICENSE
Provides-Extra: nkeys
Requires-Dist: nkeys; extra == "nkeys"
Provides-Extra: aiohttp
Requires-Dist: aiohttp; extra == "aiohttp"
Provides-Extra: fast-parse
Requires-Dist: fast-mail-parser; extra == "fast-parse"
